README.md
setup.py
rtml_distributions/Binomialdistribution.py
rtml_distributions/Gaussiandistribution.py
rtml_distributions/Generaldistribution.py
rtml_distributions/__init__.py
rtml_distributions.egg-info/PKG-INFO
rtml_distributions.egg-info/SOURCES.txt
rtml_distributions.egg-info/dependency_links.txt
rtml_distributions.egg-info/not-zip-safe
rtml_distributions.egg-info/top_level.txt