Metadata-Version: 1.0
Name: rtml-distributions
Version: 1.0
Summary: Gaussian and Binomial distributions
Home-page: UNKNOWN
Author: Rodolfo Teles
Author-email: rodolfojeronimoteles@gmail.com
License: UNKNOWN
Platform: UNKNOWN
